essentialsx/__init__.py
essentialsx/essentials.py
essentialsx-0.0.2.dist-info/LICENSE
essentialsx-0.0.2.dist-info/METADATA
essentialsx-0.0.2.dist-info/WHEEL
essentialsx-0.0.2.dist-info/top_level.txt
essentialsx-0.0.2.dist-info/RECORD
