Metadata-Version: 2.1
Name: essentialsx
Version: 0.0.2
Summary: Essential functions to be easily reused across Python projects.
Home-page: https://github.com/mistergates/essentialsx
Author: Mitch Gates
Author-email: gates55434@gmail.com
License: MIT
Keywords: core utilities,logging,hotkeys
Platform: UNKNOWN
Classifier: License :: OSI Approved :: MIT License
Classifier: Programming Language :: Python :: 3
Classifier: Programming Language :: Python :: 3.6
Classifier: Programming Language :: Python :: 3.7
Classifier: Programming Language :: Python :: 3.8
Classifier: Programming Language :: Python :: 3.9
Classifier: Operating System :: OS Independent
Requires-Dist: keyboard
Requires-Dist: rich
